README.md
setup.py
cyze/__init__.py
cyze/_cythonize.py
cyze/cyze.py
cyze.egg-info/PKG-INFO
cyze.egg-info/SOURCES.txt
cyze.egg-info/dependency_links.txt
cyze.egg-info/entry_points.txt
cyze.egg-info/requires.txt
cyze.egg-info/top_level.txt