Metadata-Version: 2.1
Name: cyze
Version: 0.1.0
Summary: Cythonize Python Project
Home-page: UNKNOWN
Author: Winter.Yu
Author-email: winter741258@gmail.com
License: Apache 2.0 License
Platform: UNKNOWN
Requires-Python: >=3.8.0
